MANIFEST.in
README
setup.py
rputils/DiceRollers.py
rputils/Main.py
rputils/PdfViewer.py
rputils/ProbabilityDensity.py
rputils/ProgramUtils.py
rputils/__init__.py
rputils/qtGUI.py
rputils/utest_DiceRollers.py
rputils/utest_ProbabilityDensity.py
rputils/utest_qtGUI.py
rputils.egg-info/PKG-INFO
rputils.egg-info/SOURCES.txt
rputils.egg-info/dependency_links.txt
rputils.egg-info/requires.txt
rputils.egg-info/top_level.txt
rputils/Resources/Config.xml
rputils/Resources/Credit.txt
rputils/Resources/__init__.py
rputils/Resources/__init__.pyc
rputils/Resources/finder.py
rputils/Resources/finder.pyc
rputils/Resources/Images/Add.png
rputils/Resources/Images/D10.png
rputils/Resources/Images/D100.png
rputils/Resources/Images/D12.png
rputils/Resources/Images/D20.png
rputils/Resources/Images/D3.png
rputils/Resources/Images/D4.png
rputils/Resources/Images/D6.png
rputils/Resources/Images/D8.png
rputils/Resources/Images/Pdf.png
rputils/Resources/Images/Remove.png
rputils/Resources/Images/Restore.png
scripts/rputils