Metadata-Version: 1.1
Name: rputils
Version: 0.151
Summary: An application for dice rolling and reading PDF files.
Home-page: https://bitbucket.org/davidcorne/roleplay-utility
Author: David Corne
Author-email: davidcorne@gmail.com
License: GPLv3
Keywords: rputils roleplay dice pdf random
Platform: UNKNOWN
Classifier: Environment :: Win32 (MS Windows)
Classifier: Intended Audience :: Developers
Classifier: License :: OSI Approved :: GNU General Public License v3 or later (GPLv3+)
Classifier: Natural Language :: English
Classifier: Operating System :: OS Independent
Classifier: Programming Language :: Python
Classifier: Topic :: Games/Entertainment
Classifier: Topic :: Games/Entertainment :: Board Games
Classifier: Topic :: Games/Entertainment :: Role-Playing
Classifier: Topic :: Multimedia :: Graphics :: Presentation
